libname/__init__.py
libname/hello.py
ColorsTextsprint-0.0.1.dist-info/METADATA
ColorsTextsprint-0.0.1.dist-info/WHEEL
ColorsTextsprint-0.0.1.dist-info/top_level.txt
ColorsTextsprint-0.0.1.dist-info/RECORD
